dj_audit/__init__.py
dj_audit/admin.py
dj_audit/middleware.py
dj_audit/models.py
dj_audit/settings.py
dj_audit/test_settings.py
dj_audit/test_urls.py
dj_audit/tests.py
dj_audit/urls.py
dj_audit/views.py
dj_audit/management/__init__.py
dj_audit/management/commands/__init__.py
dj_audit/management/commands/flush_auditlog.py
dj_audit/migrations/0001_initial.py
dj_audit/migrations/0002_auto_20211026_1018.py
dj_audit/migrations/0003_alter_auditlog_http_referer.py
dj_audit/migrations/0004_alter_auditlog_response_body.py
dj_audit/migrations/0005_alter_auditlog_user_agent.py
dj_audit/migrations/__init__.py
dj_audit/static/.gitkeep
dj_audit/static/dj_audit/css/base.css
dj_audit/static/dj_audit/js/base.js
dj_audit/templates/.gitkeep
dj_audit/templates/dj_audit/audit_list_page.html
dj_audit/templates/dj_audit/base.html
dj_audit/templates/dj_audit/request_status_page.html
dj_audit-0.1.4.dist-info/LICENSE
dj_audit-0.1.4.dist-info/METADATA
dj_audit-0.1.4.dist-info/WHEEL
dj_audit-0.1.4.dist-info/top_level.txt
dj_audit-0.1.4.dist-info/RECORD
