Metadata-Version: 2.1
Name: dj_audit
Version: 0.1.4
Summary: Django Audit is a simple Django app that tracks and logs requests to your application.
Home-page: https://github.com/Emmarex/django-audit
Download-URL: 
Author: Tairu Oluwafemi Emmanuel
Author-email: tairuoluwafemi09@gmail.com
Keywords: Django Audit,Audit,audit trail
Classifier: Natural Language :: English
Classifier: Programming Language :: Python :: 3.6
Classifier: Programming Language :: Python :: 3.7
Classifier: Programming Language :: Python :: 3.8
Classifier: Programming Language :: Python :: 3.9
Classifier: License :: OSI Approved :: Apache Software License
Classifier: Development Status :: 6 - Mature
Classifier: Intended Audience :: Developers
Classifier: Framework :: Django
Classifier: Framework :: Django :: 2.2
Classifier: Framework :: Django :: 3.0
Classifier: Framework :: Django :: 3.1
Classifier: Framework :: Django :: 3.2
Classifier: Framework :: Django :: 4.0
Requires-Python: ~=3.6
License-File: LICENSE
